MANIFEST.in
README.rst
bootstrap.py
buildout.cfg
setup.py
collective/__init__.py
collective.js.jwplayer.egg-info/PKG-INFO
collective.js.jwplayer.egg-info/SOURCES.txt
collective.js.jwplayer.egg-info/dependency_links.txt
collective.js.jwplayer.egg-info/entry_points.txt
collective.js.jwplayer.egg-info/namespace_packages.txt
collective.js.jwplayer.egg-info/not-zip-safe
collective.js.jwplayer.egg-info/requires.txt
collective.js.jwplayer.egg-info/top_level.txt
collective/js/__init__.py
collective/js/jwplayer/__init__.py
collective/js/jwplayer/config.py
collective/js/jwplayer/configure.zcml
collective/js/jwplayer/interfaces.py
collective/js/jwplayer/upgrades.py
collective/js/jwplayer/upgrades.zcml
collective/js/jwplayer/profiles/default/jsregistry.xml
collective/js/jwplayer/profiles/default/metadata.xml
collective/js/jwplayer/resources/README.html
collective/js/jwplayer/resources/jwplayer.flash.swf
collective/js/jwplayer/resources/jwplayer.html5.js
collective/js/jwplayer/resources/jwplayer.js
collective/js/jwplayer/resources/license.txt
collective/js/jwplayer/resources/6.3.3242/jwplayer.flash.swf
collective/js/jwplayer/resources/6.3.3242/jwplayer.html5.js
collective/js/jwplayer/resources/6.3.3242/jwplayer.js
docs/HISTORY.txt