Metadata-Version: 1.1
Name: collective.js.jwplayer
Version: 6.4.3359
Summary: JWPlayer resource for Plone
Home-page: https://github.com/collective/collective.js.jwplayer
Author: JeanMichel FRANCOIS aka toutpt
Author-email: toutpt@gmail.com
License: GPL
Keywords: plone jwplayer
Platform: UNKNOWN
Classifier: Environment :: Web Environment
Classifier: License :: OSI Approved :: GNU General Public License (GPL)
Classifier: Operating System :: OS Independent
Classifier: Framework :: Plone
Classifier: Framework :: Plone :: 4.0
Classifier: Framework :: Plone :: 4.1
Classifier: Framework :: Plone :: 4.2
Classifier: Framework :: Plone :: 4.3
Classifier: Programming Language :: Python
